htmlgen_mcp/__init__.py
htmlgen_mcp/config.py
htmlgen_mcp/nas_log_manager.py
htmlgen_mcp/nas_storage.py
htmlgen_mcp/web_agent_server.py
htmlgen_mcp/agents/__init__.py
htmlgen_mcp/agents/web_tools/__init__.py
htmlgen_mcp/agents/web_tools/edgeone_deploy.py
htmlgen_mcp/generative_ui/__init__.py
htmlgen_mcp/generative_ui/agent.py
htmlgen_mcp/generative_ui/config.py
htmlgen_mcp/generative_ui/models.py
htmlgen_mcp/generative_ui/processors/__init__.py
htmlgen_mcp/generative_ui/processors/post_processor.py
htmlgen_mcp/generative_ui/prompts/__init__.py
htmlgen_mcp/generative_ui/prompts/system_prompt_builder.py
htmlgen_mcp/generative_ui/tools/__init__.py
htmlgen_mcp/generative_ui/tools/endpoints_service.py
htmlgen_mcp-0.5.4.dist-info/METADATA
htmlgen_mcp-0.5.4.dist-info/WHEEL
htmlgen_mcp-0.5.4.dist-info/entry_points.txt
htmlgen_mcp-0.5.4.dist-info/top_level.txt
htmlgen_mcp-0.5.4.dist-info/RECORD
