Metadata-Version: 2.4
Name: htmlgen-mcp
Version: 0.5.4
Summary: AI-powered HTML website generator with auto-upload functionality via Model Context Protocol
Author-email: HTML Generator Team <contact@htmlgen-mcp.com>
License: MIT
Project-URL: Homepage, https://github.com/your-username/htmlgen-mcp
Project-URL: Repository, https://github.com/your-username/htmlgen-mcp
Project-URL: Issues, https://github.com/your-username/htmlgen-mcp/issues
Project-URL: Documentation, https://github.com/your-username/htmlgen-mcp/blob/main/README.md
Keywords: mcp,html,website,generator,ai,auto-upload,web-development
Classifier: Development Status :: 4 - Beta
Classifier: Intended Audience :: Developers
Classifier: License :: OSI Approved :: MIT License
Classifier: Programming Language :: Python :: 3
Classifier: Programming Language :: Python :: 3.10
Classifier: Programming Language :: Python :: 3.11
Classifier: Programming Language :: Python :: 3.12
Classifier: Topic :: Internet :: WWW/HTTP :: Site Management
Classifier: Topic :: Software Development :: Code Generators
Classifier: Topic :: Text Processing :: Markup :: HTML
Classifier: Topic :: Scientific/Engineering :: Artificial Intelligence
Requires-Python: >=3.10
Requires-Dist: click>=8.2.1
Requires-Dist: fastmcp>=2.12.3
Requires-Dist: openai>=1.91.0
Requires-Dist: python-dotenv>=1.1.1
Requires-Dist: requests>=2.31.0
Requires-Dist: cos-python-sdk-v5>=1.9.30
Requires-Dist: aiohttp>=3.8.0
Requires-Dist: uvloop>=0.19; platform_system != "Windows"
Requires-Dist: google-generativeai>=0.8.0
Provides-Extra: dev
Requires-Dist: pytest>=7.0.0; extra == "dev"
Requires-Dist: pytest-asyncio>=0.21.0; extra == "dev"
Requires-Dist: black>=23.0.0; extra == "dev"
Requires-Dist: isort>=5.12.0; extra == "dev"
Requires-Dist: flake8>=6.0.0; extra == "dev"
Requires-Dist: mypy>=1.0.0; extra == "dev"
Requires-Dist: hypothesis>=6.0.0; extra == "dev"
